rodin_gen2_server.py
rodin_gen2_mcp-0.3.6.dist-info/METADATA
rodin_gen2_mcp-0.3.6.dist-info/WHEEL
rodin_gen2_mcp-0.3.6.dist-info/entry_points.txt
rodin_gen2_mcp-0.3.6.dist-info/licenses/LICENSE
rodin_gen2_mcp-0.3.6.dist-info/RECORD
