Metadata-Version: 2.4
Name: rodin-gen2-mcp
Version: 0.3.6
Summary: MCP Server for Rodin Gen-2 3D Generation API
Project-URL: Homepage, https://github.com/TiGRoNdev/RodinGen2MCP
Project-URL: Repository, https://github.com/TiGRoNdev/RodinGen2MCP
Project-URL: Documentation, https://github.com/TiGRoNdev/RodinGen2MCP#readme
Project-URL: Bug Tracker, https://github.com/TiGRoNdev/RodinGen2MCP/issues
Author-email: Igor Nazarov <tigron.dev@gmail.com>
License: MIT
License-File: LICENSE
Keywords: 3d,ai,generation,mcp,model-context-protocol,rodin
Classifier: Development Status :: 4 - Beta
Classifier: Intended Audience :: Developers
Classifier: License :: OSI Approved :: MIT License
Classifier: Programming Language :: Python :: 3
Classifier: Programming Language :: Python :: 3.10
Classifier: Programming Language :: Python :: 3.11
Classifier: Programming Language :: Python :: 3.12
Classifier: Topic :: Scientific/Engineering :: Artificial Intelligence
Classifier: Topic :: Software Development :: Libraries :: Python Modules
Requires-Python: >=3.10
Requires-Dist: aiofiles>=23.0.0
Requires-Dist: httpx>=0.24.0
Requires-Dist: mcp>=1.2.0
Requires-Dist: python-dotenv>=1.0.0
Provides-Extra: dev
Requires-Dist: black>=23.0.0; extra == 'dev'
Requires-Dist: fastapi>=0.100.0; extra == 'dev'
Requires-Dist: httpx>=0.24.0; extra == 'dev'
Requires-Dist: pytest-asyncio>=0.21.0; extra == 'dev'
Requires-Dist: pytest-cov>=4.0.0; extra == 'dev'
Requires-Dist: pytest-mock>=3.10.0; extra == 'dev'
Requires-Dist: pytest>=7.0.0; extra == 'dev'
Requires-Dist: ruff>=0.1.0; extra == 'dev'
Requires-Dist: uvicorn>=0.23.0; extra == 'dev'
